{
  "movies": [
    {
      "movie": {
        "movieTitle": "Estoy casado, ja, ja",
        "moviePosterPath": "/64QzaWOY4AcYug8z04Spibe7FQl.jpg"
      },
      "_id": 1
    },
    {
      "movie": {
        "movieTitle": "Jaws",
        "moviePosterPath": "/l1yltvzILaZcx2jYvc5sEMkM7Eh.jpg"
      },
      "_id": 2
    },
    {
      "movie": {
        "movieTitle": "Estoy casado, ja, ja",
        "moviePosterPath": "/64QzaWOY4AcYug8z04Spibe7FQl.jpg"
      },
      "_id": 3
    },
    {
      "movie": {
        "movieTitle": "Estoy casado, ja, ja",
        "moviePosterPath": "/64QzaWOY4AcYug8z04Spibe7FQl.jpg"
      },
      "_id": 4
    },
    {
      "movie": {
        "movieTitle": "Glass Jaw",
        "moviePosterPath": "/dHf1857Y2Pmd3LPFBg09SxbLbiR.jpg"
      },
      "_id": 5
    },
    {
      "movie": {
        "movieTitle": "Jaws",
        "moviePosterPath": "/l1yltvzILaZcx2jYvc5sEMkM7Eh.jpg"
      },
      "_id": 6
    },
    {
      "movie": {
        "movieTitle": "Estoy casado, ja, ja",
        "moviePosterPath": "/64QzaWOY4AcYug8z04Spibe7FQl.jpg"
      },
      "_id": 7
    },
    {
      "movie": {
        "movieTitle": "Jaws",
        "moviePosterPath": "/l1yltvzILaZcx2jYvc5sEMkM7Eh.jpg"
      },
      "_id": 8
    },
    {
      "movie": {
        "movieTitle": "Estoy casado, ja, ja",
        "moviePosterPath": "/64QzaWOY4AcYug8z04Spibe7FQl.jpg"
      },
      "_id": 9
    },
    {
      "movie": {
        "movieTitle": "Glass Jaw",
        "moviePosterPath": "/dHf1857Y2Pmd3LPFBg09SxbLbiR.jpg"
      },
      "_id": 10
    },
    {
      "movie": {
        "movieTitle": "Glass Jaw",
        "moviePosterPath": "/dHf1857Y2Pmd3LPFBg09SxbLbiR.jpg"
      },
      "_id": 11
    },
    {
      "movie": {
        "movieTitle": "Jaws",
        "moviePosterPath": "/l1yltvzILaZcx2jYvc5sEMkM7Eh.jpg"
      },
      "_id": 12
    },
    {
      "movie": {
        "movieTitle": "A Monster Calls",
        "moviePosterPath": "/vdHUj9cyRe7fIYdJFMyc7elnawC.jpg"
      },
      "_id": 13
    },
    {
      "movie": {
        "movieTitle": "Prey",
        "moviePosterPath": "/x1vKvTX6cRwQgLX98YMUNsipJQB.jpg"
      },
      "_id": 14
    },
    {
      "movie": {
        "movieTitle": "Glass Jaw",
        "moviePosterPath": "/dHf1857Y2Pmd3LPFBg09SxbLbiR.jpg"
      },
      "_id": 15
    },
    {
      "movie": {
        "movieTitle": "Glass Jaw",
        "moviePosterPath": "/dHf1857Y2Pmd3LPFBg09SxbLbiR.jpg"
      },
      "_id": 16
    },
    {
      "movie": {
        "movieTitle": "Glass Jaw",
        "moviePosterPath": "/dHf1857Y2Pmd3LPFBg09SxbLbiR.jpg"
      },
      "_id": 17
    },
    {
      "movie": {
        "movieTitle": "Glass Jaw",
        "moviePosterPath": "/dHf1857Y2Pmd3LPFBg09SxbLbiR.jpg"
      },
      "_id": 18
    },
    {
      "movie": {
        "movieTitle": "Glass Jaw",
        "moviePosterPath": "/dHf1857Y2Pmd3LPFBg09SxbLbiR.jpg"
      },
      "_id": 19
    },
    {
      "movie": {
        "movieTitle": "Glass Jaw",
        "moviePosterPath": "/dHf1857Y2Pmd3LPFBg09SxbLbiR.jpg"
      },
      "_id": 20
    },
    {
      "movie": {
        "movieTitle": "Glass Jaw",
        "moviePosterPath": "/dHf1857Y2Pmd3LPFBg09SxbLbiR.jpg"
      },
      "_id": 21
    },
    {
      "movie": {
        "movieTitle": "Glass Jaw",
        "moviePosterPath": "/dHf1857Y2Pmd3LPFBg09SxbLbiR.jpg"
      },
      "_id": 22
    },
    {
      "movie": {
        "movieTitle": "Glass Jaw",
        "moviePosterPath": "/dHf1857Y2Pmd3LPFBg09SxbLbiR.jpg"
      },
      "_id": 23
    },
    {
      "movie": {
        "movieTitle": "Glass Jaw",
        "moviePosterPath": "/dHf1857Y2Pmd3LPFBg09SxbLbiR.jpg"
      },
      "_id": 24
    },
    {
      "movie": {
        "movieTitle": "Babylon A.D.",
        "moviePosterPath": "/eeoB2u438Z8b14HJn8TVe8X9F1U.jpg"
      },
      "_id": 25
    },
    {
      "movie": {
        "movieTitle": "Babylon A.D.",
        "moviePosterPath": "/eeoB2u438Z8b14HJn8TVe8X9F1U.jpg"
      },
      "_id": 26
    },
    {
      "movie": {
        "movieTitle": "A Monster Calls",
        "moviePosterPath": "/vdHUj9cyRe7fIYdJFMyc7elnawC.jpg"
      },
      "_id": 27
    },
    {
      "movie": {
        "movieTitle": "Prey",
        "moviePosterPath": "/x1vKvTX6cRwQgLX98YMUNsipJQB.jpg"
      },
      "_id": 28
    },
    {
      "movie": {
        "movieTitle": "A Monster Calls",
        "moviePosterPath": "/vdHUj9cyRe7fIYdJFMyc7elnawC.jpg"
      },
      "_id": 29
    },
    {
      "movie": {
        "movieTitle": "Prey",
        "moviePosterPath": "/x1vKvTX6cRwQgLX98YMUNsipJQB.jpg"
      },
      "_id": 30
    },
    {
      "movie": {
        "movieTitle": "Glass Jaw",
        "moviePosterPath": "/dHf1857Y2Pmd3LPFBg09SxbLbiR.jpg"
      },
      "_id": 31
    },
    {
      "movie": {
        "movieTitle": "Babylon A.D.",
        "moviePosterPath": "/eeoB2u438Z8b14HJn8TVe8X9F1U.jpg"
      },
      "_id": 32
    }
  ]
}